lhy_utils/__init__.py
lhy_utils/keras_to_tf.py
lhy_utils/lhy_io_utils.py
lhy_utils/lhy_log_utils.py
lhy_utils/lhy_module_utils.py
lhy_utils/lhy_net_utils.py
lhy_utils/lhy_tf_utils.py
lhy_utils/lhy_tool_utils.py
lhy_utils/nlp_logging.py
lhy_utils/test.py
lhy_utils-0.1.22.dist-info/METADATA
lhy_utils-0.1.22.dist-info/WHEEL
lhy_utils-0.1.22.dist-info/top_level.txt
lhy_utils-0.1.22.dist-info/RECORD
