Metadata-Version: 2.1
Name: lhy-utils
Version: 0.1.22
Summary: 工具箱
Home-page: https://github.com/lhy2749/lhy-utils
Author: lhy
Author-email: 379970083@qq.com
